[
    {
        "id": 1,
        "photoUrl": "https://images.pexels.com/photos/841130/pexels-photo-841130.jpeg?auto=compress&cs=tinysrgb&w=1260&h=750&dpr=1",
        "link": "https://www.mayoclinic.org/healthy-lifestyle/fitness/in-depth/exercise/art-20048389",
        "title": "Gym Exercise",
        "description": "It can feel overwhelming when you’re trying to make time for exercise. Here are some tips I give my physical therapy patients… and how I manage to keep myself moving.",
        "category": "Exercise",
        "date": "September 29 2022"
    },
    {
        "id": 1,
        "photoUrl": "https://images.pexels.com/photos/4024914/pexels-photo-4024914.jpeg?auto=compress&cs=tinysrgb&w=1260&h=750&dpr=1",
        "link": "https://www.pexels.com/photo/person-holding-barbell-841130/",
        "title": "7 benefits of regular physical activity",
        "description": "The health benefits of regular exercise and physical activity are hard to ignore. Everyone benefits from exercise, regardless of age, sex or physical ability.",
        "category": "Fitness",
        "date": "September 29 2022"
    },
    {
        "id": 3,
        "photoUrl": "https://images.pexels.com/photos/841130/pexels-photo-841130.jpeg?auto=compress&cs=tinysrgb&w=1260&h=750&dpr=1",
        "link": "https://www.mayoclinic.org/healthy-lifestyle/fitness/in-depth/exercise/art-20048389",
        "title": "Gym Exercise",
        "description": "It can feel overwhelming when you’re trying to make time for exercise. Here are some tips I give my physical therapy patients… and how I manage to keep myself moving.",
        "category": "Exercise",
        "date": "September 29 2022"
    },
    {
        "id": 4,
        "photoUrl": "https://images.pexels.com/photos/4024914/pexels-photo-4024914.jpeg?auto=compress&cs=tinysrgb&w=1260&h=750&dpr=1",
        "link": "https://www.pexels.com/photo/person-holding-barbell-841130/",
        "title": "7 benefits of regular physical activity",
        "description": "The health benefits of regular exercise and physical activity are hard to ignore. Everyone benefits from exercise, regardless of age, sex or physical ability.",
        "category": "Fitness",
        "date": "September 29 2022"
    },
    {
        "id": 5,
        "photoUrl": "https://images.pexels.com/photos/841130/pexels-photo-841130.jpeg?auto=compress&cs=tinysrgb&w=1260&h=750&dpr=1",
        "link": "https://www.mayoclinic.org/healthy-lifestyle/fitness/in-depth/exercise/art-20048389",
        "title": "Gym Exercise",
        "description": "It can feel overwhelming when you’re trying to make time for exercise. Here are some tips I give my physical therapy patients… and how I manage to keep myself moving.",
        "category": "Exercise",
        "date": "September 29 2022"
    },
    {
        "id": 6,
        "photoUrl": "https://images.pexels.com/photos/4024914/pexels-photo-4024914.jpeg?auto=compress&cs=tinysrgb&w=1260&h=750&dpr=1",
        "link": "https://www.pexels.com/photo/person-holding-barbell-841130/",
        "title": "7 benefits of regular physical activity",
        "description": "The health benefits of regular exercise and physical activity are hard to ignore. Everyone benefits from exercise, regardless of age, sex or physical ability.",
        "category": "Fitness",
        "date": "September 29 2022"
    },
    {
        "id": 7,
        "photoUrl": "https://images.pexels.com/photos/841130/pexels-photo-841130.jpeg?auto=compress&cs=tinysrgb&w=1260&h=750&dpr=1",
        "link": "https://www.mayoclinic.org/healthy-lifestyle/fitness/in-depth/exercise/art-20048389",
        "title": "Gym Exercise",
        "description": "It can feel overwhelming when you’re trying to make time for exercise. Here are some tips I give my physical therapy patients… and how I manage to keep myself moving.",
        "category": "Exercise",
        "date": "September 29 2022"
    },
    {
        "id": 8,
        "photoUrl": "https://images.pexels.com/photos/4024914/pexels-photo-4024914.jpeg?auto=compress&cs=tinysrgb&w=1260&h=750&dpr=1",
        "link": "https://www.pexels.com/photo/person-holding-barbell-841130/",
        "title": "7 benefits of regular physical activity",
        "description": "The health benefits of regular exercise and physical activity are hard to ignore. Everyone benefits from exercise, regardless of age, sex or physical ability.",
        "category": "Fitness",
        "date": "September 29 2022"
    }
]